{
    "education": [
        {
            "title": "Sept 2016 - Apr 2022",
            "cardTitle": "Bachelors of Mathematics",
            "cardSubtitle": "University of Waterloo, Ontario",
            "cardDetailedText": [
                "Majors in Combinatorics and Optimisation",
                "Minors in Computer Science",
                "Majors in Computational Mathematics",
                "Majors in Geomatics",
                "Diploma in excellence in GIS"
            ],
            "icon": {
                "src": "images/education/uwaterloo.png"
            }
        }
    ]
}